weatherbug_spark/__init__.py
weatherbug_spark/util.py
weatherbug_spark-0.0.3.dist-info/LICENSE
weatherbug_spark-0.0.3.dist-info/METADATA
weatherbug_spark-0.0.3.dist-info/WHEEL
weatherbug_spark-0.0.3.dist-info/top_level.txt
weatherbug_spark-0.0.3.dist-info/RECORD
