Metadata-Version: 2.1
Name: weatherbug-spark
Version: 0.0.3
Summary: Wrapper for WeatherBug Spark API
Home-page: https://github.com/IceBotYT/weatherbug_spark
Author: IceBotYT
Author-email: icebotyt@outlook.com
Project-URL: Bug Tracker, https://github.com/IceBotYT/weatherbug_spark/issues
Classifier: Programming Language :: Python :: 3
Classifier: License :: OSI Approved :: MIT License
Classifier: Operating System :: OS Independent
License-File: LICENSE
Requires-Dist: aiohttp (>=3.8.1)
Requires-Dist: pydantic (>=1.9.0)
